{
    "ins": {
        "ins_id": "",
        "ins_auth_cert": "cert file path",
        "ins_auth_key": "cert key",
        "ins_ver": "ver number"
    },
    "ins_perf": {
        "req_handle_timeout":0,
        "vs_switch":0
    },
    "servers": [
        {
            "id": "master002",
            "name": "",
            "scheme": "socket",
            "host": "",
            "port": 8091,
            "proxy_entry": "entry",
            "proxy_path": "/",
            "logs": "/Users/jclee/Desktop/logs",
            "libs": "/Users/jclee/Desktop/jclibs",
            "apps": []
        },
        {
            "id": "16",
            "name": "",
            "scheme": "http",
            "host": "",
            "port": 8081,
            "proxy_entry": "entry",
            "proxy_path": "/",
            "logs": "/Users/jclee/Desktop/logs",
            "domain_visit":"/server/index",
            "libs": "/Users/jclee/Desktop/jclibs",
            "master": "jcs://e.local:8091/",
            "apps": [
                {
                    "app_id": "88888888",
                    "app_code": "project",
                    "app_name": "项目管理服务",
                    "dev_name": "jeancoder",
                    "org_name": "com",
                    "app_ver": "1.0",
                    "source_type": "binary",
                    "lans": "groovy",
                    "app_base":"/Users/jclee/Documents/devworkspace/jcworkspace/jcapps/app_project",
                    "config": {
                        "description": "项目管理服务",
                        "index":"index"
                    }
                },
                {
                    "app_id": "88888888",
                    "app_code": "crm",
                    "app_name": "会员管理服务",
                    "dev_name": "jeancoder",
                    "org_name": "com",
                    "app_ver": "1.0",
                    "source_type": "binary",
                    "lans": "groovy",
                    "app_base":"/Users/jclee/Documents/devworkspace/jcworkspace/jcapps/app_crm",
                    "config": {
                        "description": "会员管理服务",
                        "index":"index"
                    }
                },
                {
                    "app_id": "88888888",
                    "app_code": "ticketingsys",
                    "app_name": "影院管理服务",
                    "dev_name": "jeancoder",
                    "org_name": "com",
                    "app_ver": "1.0",
                    "source_type": "binary",
                    "lans": "groovy",
                    "app_base":"/Users/jclee/Documents/devworkspace/jcworkspace/jcapps/app_ticketingsys",
                    "config": {
                        "description": "影院管理服务",
                        "index":"index"
                    }
                },
                {
                    "app_id": "88888888",
                    "app_code": "scm",
                    "app_name": "进销存管理服务",
                    "dev_name": "jeancoder",
                    "org_name": "com",
                    "app_ver": "1.0",
                    "source_type": "binary",
                    "lans": "groovy",
                    "app_base":"/Users/jclee/Documents/devworkspace/jcworkspace/jcapps/app_scm",
                    "config": {
                        "description": "进销存管理服务",
                        "index":"index"
                    }
                },
                {
                    "app_id": "88888888",
                    "app_code": "trade",
                    "app_name": "交易管理服务",
                    "dev_name": "jeancoder",
                    "org_name": "com",
                    "app_ver": "1.0",
                    "source_type": "binary",
                    "lans": "groovy",
                    "app_base":"/Users/jclee/Documents/devworkspace/jcworkspace/jcapps/app_trade",
                    "config": {
                        "description": "交易管理服务",
                        "index":"index"
                    }
                },
                {
                    "app_id": "88888888",
                    "app_code": "market",
                    "app_name": "运营支持服务",
                    "dev_name": "jeancoder",
                    "org_name": "com",
                    "app_ver": "1.0",
                    "source_type": "binary",
                    "lans": "groovy",
                    "app_base":"/Users/jclee/Documents/devworkspace/jcworkspace/jcapps/app_market",
                    "config": {
                        "description": "运营支持服务",
                        "index":"index"
                    }
                },
                {
                    "app_id": "88888888",
                    "app_code": "general_api",
                    "app_name": "接口服务",
                    "dev_name": "lengjiabao",
                    "org_name": "com",
                    "app_ver": "1.0",
                    "source_type": "binary",
                    "lans": "groovy",
                    "app_base":"/Users/jclee/Documents/devworkspace/jcworkspace/jcapps/92yp_general_api",
                    "config": {
                        "description": "接口服务",
                        "index":"index"
                    }
                }
            ]
        }
    ]
}